fritzbox_tray/__init__.py
fritzbox_tray/__main__.py
fritzbox_tray/resources/ft.ico
fritzbox_tray-1.0.74.dist-info/LICENSE
fritzbox_tray-1.0.74.dist-info/METADATA
fritzbox_tray-1.0.74.dist-info/WHEEL
fritzbox_tray-1.0.74.dist-info/entry_points.txt
fritzbox_tray-1.0.74.dist-info/top_level.txt
fritzbox_tray-1.0.74.dist-info/RECORD
