Metadata-Version: 2.1
Name: fritzbox-tray
Version: 1.0.74
Summary: A system tray application for interacting with FRITZ!Box devices.
Home-page: https://github.com/aviolaris/fritzbox-tray
Author: Andreas Violaris
Keywords: fritz,fritzbox,fritz-box,fritzbox-tray,fritzbox_tray,avm-fritz,tray,python,pypi,python3,tray,tray-application,pypi-package,tray-app
Classifier: Development Status :: 5 - Production/Stable
Classifier: Intended Audience :: End Users/Desktop
Classifier: Operating System :: Microsoft :: Windows
Classifier: Operating System :: POSIX :: Linux
Classifier: Operating System :: MacOS
Classifier: Programming Language :: Python :: 3.6
Classifier: Programming Language :: Python :: 3.7
Classifier: Programming Language :: Python :: 3.8
Classifier: Programming Language :: Python :: 3.9
Classifier: Programming Language :: Python :: 3.10
Classifier: Programming Language :: Python :: 3.11
Classifier: License :: OSI Approved :: GNU General Public License v3 (GPLv3)
License-File: LICENSE
Requires-Dist: charset-normalizer ==3.4.1
Requires-Dist: certifi ==2024.12.14
Requires-Dist: idna ==3.10
Requires-Dist: Pillow ==11.1.0
Requires-Dist: pystray ==0.19.5
Requires-Dist: requests ==2.32.3
Requires-Dist: urllib3 ==2.3.0
Requires-Dist: six ==1.17.0
